Metadata-Version: 2.1
Name: uaddresspacy
Version: 1.0.0
Summary: Ukrainian address parser
Home-page: https://github.com/martinjack/uaddresspacy
Author: Evgen Kytonin
License: MIT
Keywords: nlp,ukraine,address,research,parsing
Platform: UNKNOWN
Classifier: Development Status :: 5 - Production/Stable
Classifier: Intended Audience :: Developers
Classifier: Intended Audience :: Science/Research
Classifier: License :: OSI Approved :: MIT License
Classifier: Topic :: Software Development :: Libraries :: Python Modules
Classifier: Topic :: Scientific/Engineering
Classifier: Topic :: Scientific/Engineering :: Information Analysis
